django_k8s_health_check/__init__.py
django_k8s_health_check/apps.py
django_k8s_health_check/middleware.py
django_k8s_health_check/serializer.py
django_k8s_health_check/settings.py
django_k8s_health_check/utils.py
django_k8s_health_check/views.py
django_k8s_health_check/management/__init__.py
django_k8s_health_check/management/commands/__init__.py
django_k8s_health_check/management/commands/health_check.py
django_k8s_health_check-1.2.0.dist-info/LICENSE
django_k8s_health_check-1.2.0.dist-info/METADATA
django_k8s_health_check-1.2.0.dist-info/WHEEL
django_k8s_health_check-1.2.0.dist-info/top_level.txt
django_k8s_health_check-1.2.0.dist-info/RECORD
