Metadata-Version: 2.1
Name: django-k8s-health-check
Version: 1.2.0
Summary: Django Health Check
Home-page: https://github.com/shinneider/django-k8s-health-check
Author: Shinneider Libanio da Silva
Author-email: shinneider-libanio@hotmail.com
License: MIT
Classifier: Development Status :: 4 - Beta
Classifier: Environment :: Web Environment
Classifier: Framework :: Django
Classifier: Intended Audience :: Developers
Classifier: License :: OSI Approved :: MIT License
Classifier: Operating System :: OS Independent
Classifier: Programming Language :: Python
Classifier: Programming Language :: Python :: 3
Classifier: Programming Language :: Python :: 3.5
Classifier: Programming Language :: Python :: 3.6
Classifier: Programming Language :: Python :: 3.7
Classifier: Topic :: Internet :: WWW/HTTP
Classifier: Topic :: Software Development :: Libraries :: Python Modules
Requires-Python: >=3.3
License-File: LICENSE
Requires-Dist: django
Requires-Dist: djangorestframework
Provides-Extra: code-quality
Requires-Dist: isort ; extra == 'code-quality'
Requires-Dist: bandit ; extra == 'code-quality'
Requires-Dist: xenon ; extra == 'code-quality'
Provides-Extra: dev
Requires-Dist: autopep8 ; extra == 'dev'
